CHANGES.txt
README.txt
bootstrap.py
buildout.cfg
setup.cfg
setup.py
src/repoze/__init__.py
src/repoze.bfg.htmlpage.egg-info/PKG-INFO
src/repoze.bfg.htmlpage.egg-info/SOURCES.txt
src/repoze.bfg.htmlpage.egg-info/dependency_links.txt
src/repoze.bfg.htmlpage.egg-info/namespace_packages.txt
src/repoze.bfg.htmlpage.egg-info/not-zip-safe
src/repoze.bfg.htmlpage.egg-info/requires.txt
src/repoze.bfg.htmlpage.egg-info/top_level.txt
src/repoze/bfg/__init__.py
src/repoze/bfg/htmlpage/__init__.py
src/repoze/bfg/htmlpage/api.py
src/repoze/bfg/htmlpage/configure.zcml
src/repoze/bfg/htmlpage/interfaces.py
src/repoze/bfg/htmlpage/meta.zcml
src/repoze/bfg/htmlpage/template.py
src/repoze/bfg/htmlpage/template.txt
src/repoze/bfg/htmlpage/zcml.py
src/repoze/bfg/htmlpage/zcml.txt
src/repoze/bfg/htmlpage/tests/__init__.py
src/repoze/bfg/htmlpage/tests/test_doctests.py
src/repoze/bfg/htmlpage/tests/templates/example.css
src/repoze/bfg/htmlpage/tests/templates/example.html
src/repoze/bfg/htmlpage/tests/templates/example.xss